customer_rating_library/__init__.py
customer_rating_library/customer_rating_library.py
customer_rating_library-0.3.dist-info/METADATA
customer_rating_library-0.3.dist-info/WHEEL
customer_rating_library-0.3.dist-info/top_level.txt
customer_rating_library-0.3.dist-info/RECORD
