Metadata-Version: 2.1
Name: customer-rating-library
Version: 0.3
Summary: A library to calculate percentage for the customer ratings.
Author: Deekshiya
Author-email: deekshiya19@gmail.com
Classifier: Programming Language :: Python :: 3
Classifier: License :: OSI Approved :: MIT License
Classifier: Operating System :: OS Independent
Requires-Python: >=3.6
